{
    "family-tree": [
        {
            "relation": "father-of",
            "subject": "Muhammed",
            "object": "Agnieszka"
        },
        {
            "relation": "mother-of",
            "subject": "Ava",
            "object": "Agnieszka"
        }
    ],
    "country": "North Wumponia",
    "test-results": [
        {
            "type": "bloodtype-test",
            "person": "Ava",
            "result": "A"
        }
    ],
    "queries": [
        {
            "type": "bloodtype",
            "person": "Muhammed"
        }
    ]
}